django_access_and_compliance
