Metadata-Version: 2.1
Name: django-access-and-compliance
Version: 0.1.5
Summary: A Django application for verifying acceptance of the University of         Michigan's Data Access and Compliance Policy
Home-page: UNKNOWN
Author: Jonathon Yu
License: UNKNOWN
Platform: UNKNOWN
Classifier: Environment :: Web Environment
Classifier: Framework :: Django
Classifier: License :: OSI Approved :: MIT License
Classifier: Operating System :: OS Independent
Classifier: Programming Language :: Python
Classifier: Programming Language :: Python :: 3.6
Classifier: Topic :: Internet :: WWW/HTTP
